pybottle/__init__.py
pybottle/bottle.py
pybottle/ecdh.py
pybottle/errors.py
pybottle/idcard.py
pybottle/keychain.py
pybottle/membership.py
pybottle/opener.py
pybottle/pkix.py
pybottle/short.py
pybottle/sign.py
pybottle/testkeys.py
pybottle/utils.py
pybottle-0.1.3.dist-info/licenses/LICENSE
pybottle-0.1.3.dist-info/METADATA
pybottle-0.1.3.dist-info/WHEEL
pybottle-0.1.3.dist-info/top_level.txt
pybottle-0.1.3.dist-info/RECORD
