Metadata-Version: 2.4
Name: pybottle
Version: 0.1.3
Summary: Cryptographic message containers with signing and encryption
Author-email: Mark Karpelès <mark@klb.jp>
License-Expression: MIT
Project-URL: Homepage, https://github.com/KarpelesLab/pybottle
Project-URL: Repository, https://github.com/KarpelesLab/pybottle
Project-URL: Issues, https://github.com/KarpelesLab/pybottle/issues
Classifier: Development Status :: 3 - Alpha
Classifier: Intended Audience :: Developers
Classifier: Programming Language :: Python :: 3
Classifier: Programming Language :: Python :: 3.10
Classifier: Programming Language :: Python :: 3.11
Classifier: Programming Language :: Python :: 3.12
Classifier: Topic :: Security :: Cryptography
Requires-Python: >=3.10
License-File: LICENSE
Requires-Dist: cryptography>=41.0.0
Requires-Dist: cbor2>=5.4.0
Provides-Extra: dev
Requires-Dist: pytest>=7.0.0; extra == "dev"
Requires-Dist: pytest-cov>=4.0.0; extra == "dev"
Dynamic: license-file
